<annotation>
	<folder>Drawings 1120</folder>
	<filename>8756-4-0081.tif</filename>
	<path>D:\Work\Autolabel\Drawings 1120\8756-4-0081.tif</path>
	<source>
		<database>Unknown</database>
	</source>
	<size>
		<width>7306</width>
		<height>4763</height>
		<depth>3</depth>
	</size>
	<segmented>0</segmented>
	<object>
		<name>Panel Instrument</name>
		<pose>Unspecified</pose>
		<truncated>0</truncated>
		<difficult>0</difficult>
		<bndbox>
			<xmin>1270</xmin>
			<ymin>913</ymin>
			<xmax>1384</xmax>
			<ymax>1029</ymax>
		</bndbox>
	</object>
	<object>
		<name>Inline Instrument</name>
		<pose>Unspecified</pose>
		<truncated>0</truncated>
		<difficult>0</difficult>
		<bndbox>
			<xmin>1276</xmin>
			<ymin>1124</ymin>
			<xmax>1392</xmax>
			<ymax>1231</ymax>
		</bndbox>
	</object>
	<object>
		<name>Inline Instrument</name>
		<pose>Unspecified</pose>
		<truncated>0</truncated>
		<difficult>0</difficult>
		<bndbox>
			<xmin>1009</xmin>
			<ymin>1495</ymin>
			<xmax>1125</xmax>
			<ymax>1602</ymax>
		</bndbox>
	</object>
	<object>
		<name>Inline Instrument</name>
		<pose>Unspecified</pose>
		<truncated>0</truncated>
		<difficult>0</difficult>
		<bndbox>
			<xmin>1153</xmin>
			<ymin>1690</ymin>
			<xmax>1263</xmax>
			<ymax>1808</ymax>
		</bndbox>
	</object>
	<object>
		<name>Inline Instrument</name>
		<pose>Unspecified</pose>
		<truncated>0</truncated>
		<difficult>0</difficult>
		<bndbox>
			<xmin>959</xmin>
			<ymin>1611</ymin>
			<xmax>1069</xmax>
			<ymax>1729</ymax>
		</bndbox>
	</object>
	<object>
		<name>Inline Instrument</name>
		<pose>Unspecified</pose>
		<truncated>0</truncated>
		<difficult>0</difficult>
		<bndbox>
			<xmin>799</xmin>
			<ymin>1374</ymin>
			<xmax>907</xmax>
			<ymax>1493</ymax>
		</bndbox>
	</object>
	<object>
		<name>Inline Instrument</name>
		<pose>Unspecified</pose>
		<truncated>0</truncated>
		<difficult>0</difficult>
		<bndbox>
			<xmin>625</xmin>
			<ymin>1470</ymin>
			<xmax>745</xmax>
			<ymax>1589</ymax>
		</bndbox>
	</object>
	<object>
		<name>Inline Instrument</name>
		<pose>Unspecified</pose>
		<truncated>0</truncated>
		<difficult>0</difficult>
		<bndbox>
			<xmin>1031</xmin>
			<ymin>1915</ymin>
			<xmax>1151</xmax>
			<ymax>2034</ymax>
		</bndbox>
	</object>
	<object>
		<name>Inline Instrument</name>
		<pose>Unspecified</pose>
		<truncated>0</truncated>
		<difficult>0</difficult>
		<bndbox>
			<xmin>787</xmin>
			<ymin>1714</ymin>
			<xmax>907</xmax>
			<ymax>1833</ymax>
		</bndbox>
	</object>
	<object>
		<name>Inline Instrument</name>
		<pose>Unspecified</pose>
		<truncated>0</truncated>
		<difficult>0</difficult>
		<bndbox>
			<xmin>632</xmin>
			<ymin>1778</ymin>
			<xmax>752</xmax>
			<ymax>1897</ymax>
		</bndbox>
	</object>
	<object>
		<name>Inline Instrument</name>
		<pose>Unspecified</pose>
		<truncated>0</truncated>
		<difficult>0</difficult>
		<bndbox>
			<xmin>801</xmin>
			<ymin>3618</ymin>
			<xmax>921</xmax>
			<ymax>3737</ymax>
		</bndbox>
	</object>
	<object>
		<name>Inline Instrument</name>
		<pose>Unspecified</pose>
		<truncated>0</truncated>
		<difficult>0</difficult>
		<bndbox>
			<xmin>1016</xmin>
			<ymin>3800</ymin>
			<xmax>1136</xmax>
			<ymax>3919</ymax>
		</bndbox>
	</object>
	<object>
		<name>Inline Instrument</name>
		<pose>Unspecified</pose>
		<truncated>0</truncated>
		<difficult>0</difficult>
		<bndbox>
			<xmin>1145</xmin>
			<ymin>3802</ymin>
			<xmax>1265</xmax>
			<ymax>3921</ymax>
		</bndbox>
	</object>
	<object>
		<name>Inline Instrument</name>
		<pose>Unspecified</pose>
		<truncated>0</truncated>
		<difficult>0</difficult>
		<bndbox>
			<xmin>1607</xmin>
			<ymin>3633</ymin>
			<xmax>1710</xmax>
			<ymax>3742</ymax>
		</bndbox>
	</object>
	<object>
		<name>Inline Instrument</name>
		<pose>Unspecified</pose>
		<truncated>0</truncated>
		<difficult>0</difficult>
		<bndbox>
			<xmin>1601</xmin>
			<ymin>3395</ymin>
			<xmax>1704</xmax>
			<ymax>3504</ymax>
		</bndbox>
	</object>
	<object>
		<name>Inline Instrument</name>
		<pose>Unspecified</pose>
		<truncated>0</truncated>
		<difficult>0</difficult>
		<bndbox>
			<xmin>2028</xmin>
			<ymin>3339</ymin>
			<xmax>2131</xmax>
			<ymax>3448</ymax>
		</bndbox>
	</object>
	<object>
		<name>Inline Instrument</name>
		<pose>Unspecified</pose>
		<truncated>0</truncated>
		<difficult>0</difficult>
		<bndbox>
			<xmin>1839</xmin>
			<ymin>3492</ymin>
			<xmax>1942</xmax>
			<ymax>3601</ymax>
		</bndbox>
	</object>
	<object>
		<name>Inline Instrument</name>
		<pose>Unspecified</pose>
		<truncated>0</truncated>
		<difficult>0</difficult>
		<bndbox>
			<xmin>1787</xmin>
			<ymin>3601</ymin>
			<xmax>1890</xmax>
			<ymax>3710</ymax>
		</bndbox>
	</object>
	<object>
		<name>Inline Instrument</name>
		<pose>Unspecified</pose>
		<truncated>0</truncated>
		<difficult>0</difficult>
		<bndbox>
			<xmin>2160</xmin>
			<ymin>3833</ymin>
			<xmax>2263</xmax>
			<ymax>3942</ymax>
		</bndbox>
	</object>
	<object>
		<name>Inline Instrument</name>
		<pose>Unspecified</pose>
		<truncated>0</truncated>
		<difficult>0</difficult>
		<bndbox>
			<xmin>2158</xmin>
			<ymin>3831</ymin>
			<xmax>2261</xmax>
			<ymax>3940</ymax>
		</bndbox>
	</object>
	<object>
		<name>Inline Instrument</name>
		<pose>Unspecified</pose>
		<truncated>0</truncated>
		<difficult>0</difficult>
		<bndbox>
			<xmin>3888</xmin>
			<ymin>3535</ymin>
			<xmax>4008</xmax>
			<ymax>3656</ymax>
		</bndbox>
	</object>
	<object>
		<name>Inline Instrument</name>
		<pose>Unspecified</pose>
		<truncated>0</truncated>
		<difficult>0</difficult>
		<bndbox>
			<xmin>3654</xmin>
			<ymin>3361</ymin>
			<xmax>3774</xmax>
			<ymax>3482</ymax>
		</bndbox>
	</object>
	<object>
		<name>Inline Instrument</name>
		<pose>Unspecified</pose>
		<truncated>0</truncated>
		<difficult>0</difficult>
		<bndbox>
			<xmin>4021</xmin>
			<ymin>3272</ymin>
			<xmax>4141</xmax>
			<ymax>3393</ymax>
		</bndbox>
	</object>
	<object>
		<name>Inline Instrument</name>
		<pose>Unspecified</pose>
		<truncated>0</truncated>
		<difficult>0</difficult>
		<bndbox>
			<xmin>3318</xmin>
			<ymin>2936</ymin>
			<xmax>3438</xmax>
			<ymax>3057</ymax>
		</bndbox>
	</object>
	<object>
		<name>Panel Instrument</name>
		<pose>Unspecified</pose>
		<truncated>0</truncated>
		<difficult>0</difficult>
		<bndbox>
			<xmin>4177</xmin>
			<ymin>2656</ymin>
			<xmax>4291</xmax>
			<ymax>2772</ymax>
		</bndbox>
	</object>
	<object>
		<name>Inline Instrument</name>
		<pose>Unspecified</pose>
		<truncated>0</truncated>
		<difficult>0</difficult>
		<bndbox>
			<xmin>4472</xmin>
			<ymin>2854</ymin>
			<xmax>4592</xmax>
			<ymax>2975</ymax>
		</bndbox>
	</object>
	<object>
		<name>Inline Instrument</name>
		<pose>Unspecified</pose>
		<truncated>0</truncated>
		<difficult>0</difficult>
		<bndbox>
			<xmin>4109</xmin>
			<ymin>2847</ymin>
			<xmax>4229</xmax>
			<ymax>2968</ymax>
		</bndbox>
	</object>
	<object>
		<name>Inline Instrument</name>
		<pose>Unspecified</pose>
		<truncated>0</truncated>
		<difficult>0</difficult>
		<bndbox>
			<xmin>4033</xmin>
			<ymin>2757</ymin>
			<xmax>4153</xmax>
			<ymax>2878</ymax>
		</bndbox>
	</object>
	<object>
		<name>Panel Instrument</name>
		<pose>Unspecified</pose>
		<truncated>0</truncated>
		<difficult>0</difficult>
		<bndbox>
			<xmin>4719</xmin>
			<ymin>2920</ymin>
			<xmax>4833</xmax>
			<ymax>3036</ymax>
		</bndbox>
	</object>
	<object>
		<name>Inline Instrument</name>
		<pose>Unspecified</pose>
		<truncated>0</truncated>
		<difficult>0</difficult>
		<bndbox>
			<xmin>4289</xmin>
			<ymin>2780</ymin>
			<xmax>4409</xmax>
			<ymax>2901</ymax>
		</bndbox>
	</object>
	<object>
		<name>Inline Instrument</name>
		<pose>Unspecified</pose>
		<truncated>0</truncated>
		<difficult>0</difficult>
		<bndbox>
			<xmin>4303</xmin>
			<ymin>3365</ymin>
			<xmax>4401</xmax>
			<ymax>3472</ymax>
		</bndbox>
	</object>
	<object>
		<name>Inline Instrument</name>
		<pose>Unspecified</pose>
		<truncated>0</truncated>
		<difficult>0</difficult>
		<bndbox>
			<xmin>4495</xmin>
			<ymin>3624</ymin>
			<xmax>4615</xmax>
			<ymax>3745</ymax>
		</bndbox>
	</object>
	<object>
		<name>Inline Instrument</name>
		<pose>Unspecified</pose>
		<truncated>0</truncated>
		<difficult>0</difficult>
		<bndbox>
			<xmin>5124</xmin>
			<ymin>3858</ymin>
			<xmax>5225</xmax>
			<ymax>3983</ymax>
		</bndbox>
	</object>
	<object>
		<name>Inline Instrument</name>
		<pose>Unspecified</pose>
		<truncated>0</truncated>
		<difficult>0</difficult>
		<bndbox>
			<xmin>4958</xmin>
			<ymin>3798</ymin>
			<xmax>5078</xmax>
			<ymax>3919</ymax>
		</bndbox>
	</object>
	<object>
		<name>Panel Instrument</name>
		<pose>Unspecified</pose>
		<truncated>0</truncated>
		<difficult>0</difficult>
		<bndbox>
			<xmin>6226</xmin>
			<ymin>1747</ymin>
			<xmax>6340</xmax>
			<ymax>1863</ymax>
		</bndbox>
	</object>
	<object>
		<name>Inline Instrument</name>
		<pose>Unspecified</pose>
		<truncated>0</truncated>
		<difficult>0</difficult>
		<bndbox>
			<xmin>6140</xmin>
			<ymin>3761</ymin>
			<xmax>6238</xmax>
			<ymax>3872</ymax>
		</bndbox>
	</object>
	<object>
		<name>Inline Instrument</name>
		<pose>Unspecified</pose>
		<truncated>0</truncated>
		<difficult>0</difficult>
		<bndbox>
			<xmin>6339</xmin>
			<ymin>3755</ymin>
			<xmax>6437</xmax>
			<ymax>3866</ymax>
		</bndbox>
	</object>
	<object>
		<name>Panel Instrument</name>
		<pose>Unspecified</pose>
		<truncated>0</truncated>
		<difficult>0</difficult>
		<bndbox>
			<xmin>5658</xmin>
			<ymin>3218</ymin>
			<xmax>5772</xmax>
			<ymax>3334</ymax>
		</bndbox>
	</object>
	<object>
		<name>Inline Instrument</name>
		<pose>Unspecified</pose>
		<truncated>0</truncated>
		<difficult>0</difficult>
		<bndbox>
			<xmin>5738</xmin>
			<ymin>2946</ymin>
			<xmax>5836</xmax>
			<ymax>3057</ymax>
		</bndbox>
	</object>
	<object>
		<name>Inline Instrument</name>
		<pose>Unspecified</pose>
		<truncated>0</truncated>
		<difficult>0</difficult>
		<bndbox>
			<xmin>5668</xmin>
			<ymin>3083</ymin>
			<xmax>5766</xmax>
			<ymax>3194</ymax>
		</bndbox>
	</object>
	<object>
		<name>Inline Instrument</name>
		<pose>Unspecified</pose>
		<truncated>0</truncated>
		<difficult>0</difficult>
		<bndbox>
			<xmin>5784</xmin>
			<ymin>2721</ymin>
			<xmax>5882</xmax>
			<ymax>2832</ymax>
		</bndbox>
	</object>
	<object>
		<name>Inline Instrument</name>
		<pose>Unspecified</pose>
		<truncated>0</truncated>
		<difficult>0</difficult>
		<bndbox>
			<xmin>6499</xmin>
			<ymin>2336</ymin>
			<xmax>6610</xmax>
			<ymax>2448</ymax>
		</bndbox>
	</object>
	<object>
		<name>Inline Instrument</name>
		<pose>Unspecified</pose>
		<truncated>0</truncated>
		<difficult>0</difficult>
		<bndbox>
			<xmin>6235</xmin>
			<ymin>2014</ymin>
			<xmax>6333</xmax>
			<ymax>2125</ymax>
		</bndbox>
	</object>
	<object>
		<name>Inline Instrument</name>
		<pose>Unspecified</pose>
		<truncated>0</truncated>
		<difficult>0</difficult>
		<bndbox>
			<xmin>6480</xmin>
			<ymin>2788</ymin>
			<xmax>6579</xmax>
			<ymax>2899</ymax>
		</bndbox>
	</object>
	<object>
		<name>Inline Instrument</name>
		<pose>Unspecified</pose>
		<truncated>0</truncated>
		<difficult>0</difficult>
		<bndbox>
			<xmin>6307</xmin>
			<ymin>2955</ymin>
			<xmax>6412</xmax>
			<ymax>3048</ymax>
		</bndbox>
	</object>
	<object>
		<name>Inline Instrument</name>
		<pose>Unspecified</pose>
		<truncated>0</truncated>
		<difficult>0</difficult>
		<bndbox>
			<xmin>6177</xmin>
			<ymin>3263</ymin>
			<xmax>6282</xmax>
			<ymax>3356</ymax>
		</bndbox>
	</object>
	<object>
		<name>Inline Instrument</name>
		<pose>Unspecified</pose>
		<truncated>0</truncated>
		<difficult>0</difficult>
		<bndbox>
			<xmin>6335</xmin>
			<ymin>3263</ymin>
			<xmax>6440</xmax>
			<ymax>3356</ymax>
		</bndbox>
	</object>
	<object>
		<name>Panel Instrument</name>
		<pose>Unspecified</pose>
		<truncated>0</truncated>
		<difficult>0</difficult>
		<bndbox>
			<xmin>6333</xmin>
			<ymin>3436</ymin>
			<xmax>6447</xmax>
			<ymax>3552</ymax>
		</bndbox>
	</object>
	<object>
		<name>Inline Instrument</name>
		<pose>Unspecified</pose>
		<truncated>0</truncated>
		<difficult>0</difficult>
		<bndbox>
			<xmin>6515</xmin>
			<ymin>3246</ymin>
			<xmax>6623</xmax>
			<ymax>3348</ymax>
		</bndbox>
	</object>
	<object>
		<name>Inline Instrument</name>
		<pose>Unspecified</pose>
		<truncated>0</truncated>
		<difficult>0</difficult>
		<bndbox>
			<xmin>7065</xmin>
			<ymin>2391</ymin>
			<xmax>7176</xmax>
			<ymax>2504</ymax>
		</bndbox>
	</object>
	<object>
		<name>Inline Instrument</name>
		<pose>Unspecified</pose>
		<truncated>0</truncated>
		<difficult>0</difficult>
		<bndbox>
			<xmin>6840</xmin>
			<ymin>2739</ymin>
			<xmax>6939</xmax>
			<ymax>2850</ymax>
		</bndbox>
	</object>
	<object>
		<name>Inline Instrument</name>
		<pose>Unspecified</pose>
		<truncated>0</truncated>
		<difficult>0</difficult>
		<bndbox>
			<xmin>6599</xmin>
			<ymin>1930</ymin>
			<xmax>6710</xmax>
			<ymax>2043</ymax>
		</bndbox>
	</object>
	<object>
		<name>Inline Instrument</name>
		<pose>Unspecified</pose>
		<truncated>0</truncated>
		<difficult>0</difficult>
		<bndbox>
			<xmin>6790</xmin>
			<ymin>1972</ymin>
			<xmax>6912</xmax>
			<ymax>2091</ymax>
		</bndbox>
	</object>
	<object>
		<name>Inline Instrument</name>
		<pose>Unspecified</pose>
		<truncated>0</truncated>
		<difficult>0</difficult>
		<bndbox>
			<xmin>6963</xmin>
			<ymin>2088</ymin>
			<xmax>7074</xmax>
			<ymax>2201</ymax>
		</bndbox>
	</object>
	<object>
		<name>Panel Instrument</name>
		<pose>Unspecified</pose>
		<truncated>0</truncated>
		<difficult>0</difficult>
		<bndbox>
			<xmin>6772</xmin>
			<ymin>1810</ymin>
			<xmax>6910</xmax>
			<ymax>1941</ymax>
		</bndbox>
	</object>
	<object>
		<name>Panel Instrument</name>
		<pose>Unspecified</pose>
		<truncated>0</truncated>
		<difficult>0</difficult>
		<bndbox>
			<xmin>6944</xmin>
			<ymin>1815</ymin>
			<xmax>7082</xmax>
			<ymax>1946</ymax>
		</bndbox>
	</object>
	<object>
		<name>Inline Instrument</name>
		<pose>Unspecified</pose>
		<truncated>0</truncated>
		<difficult>0</difficult>
		<bndbox>
			<xmin>6581</xmin>
			<ymin>1825</ymin>
			<xmax>6692</xmax>
			<ymax>1938</ymax>
		</bndbox>
	</object>
	<object>
		<name>Panel Instrument</name>
		<pose>Unspecified</pose>
		<truncated>0</truncated>
		<difficult>0</difficult>
		<bndbox>
			<xmin>6554</xmin>
			<ymin>1329</ymin>
			<xmax>6654</xmax>
			<ymax>1430</ymax>
		</bndbox>
	</object>
	<object>
		<name>Panel Instrument</name>
		<pose>Unspecified</pose>
		<truncated>0</truncated>
		<difficult>0</difficult>
		<bndbox>
			<xmin>6479</xmin>
			<ymin>1322</ymin>
			<xmax>6561</xmax>
			<ymax>1435</ymax>
		</bndbox>
	</object>
	<object>
		<name>Panel Instrument</name>
		<pose>Unspecified</pose>
		<truncated>0</truncated>
		<difficult>0</difficult>
		<bndbox>
			<xmin>6380</xmin>
			<ymin>1323</ymin>
			<xmax>6481</xmax>
			<ymax>1441</ymax>
		</bndbox>
	</object>
	<object>
		<name>Inline Instrument</name>
		<pose>Unspecified</pose>
		<truncated>0</truncated>
		<difficult>0</difficult>
		<bndbox>
			<xmin>6575</xmin>
			<ymin>3792</ymin>
			<xmax>6673</xmax>
			<ymax>3903</ymax>
		</bndbox>
	</object>
	<object>
		<name>Inline Instrument</name>
		<pose>Unspecified</pose>
		<truncated>0</truncated>
		<difficult>0</difficult>
		<bndbox>
			<xmin>6772</xmin>
			<ymin>3791</ymin>
			<xmax>6870</xmax>
			<ymax>3902</ymax>
		</bndbox>
	</object>
	<object>
		<name>Inline Instrument</name>
		<pose>Unspecified</pose>
		<truncated>0</truncated>
		<difficult>0</difficult>
		<bndbox>
			<xmin>6939</xmin>
			<ymin>3471</ymin>
			<xmax>7052</xmax>
			<ymax>3583</ymax>
		</bndbox>
	</object>
	<object>
		<name>Inline Instrument</name>
		<pose>Unspecified</pose>
		<truncated>0</truncated>
		<difficult>0</difficult>
		<bndbox>
			<xmin>6910</xmin>
			<ymin>3887</ymin>
			<xmax>7004</xmax>
			<ymax>3987</ymax>
		</bndbox>
	</object>
	<object>
		<name>Inline Instrument</name>
		<pose>Unspecified</pose>
		<truncated>0</truncated>
		<difficult>0</difficult>
		<bndbox>
			<xmin>6908</xmin>
			<ymin>3800</ymin>
			<xmax>7009</xmax>
			<ymax>3894</ymax>
		</bndbox>
	</object>
	<object>
		<name>Inline Instrument</name>
		<pose>Unspecified</pose>
		<truncated>0</truncated>
		<difficult>0</difficult>
		<bndbox>
			<xmin>6908</xmin>
			<ymin>3712</ymin>
			<xmax>7006</xmax>
			<ymax>3805</ymax>
		</bndbox>
	</object>
</annotation>
